shutill/__init__.py
shutill/__main__.py
shutill-3.1.dist-info/METADATA
shutill-3.1.dist-info/WHEEL
shutill-3.1.dist-info/entry_points.txt
shutill-3.1.dist-info/top_level.txt
shutill-3.1.dist-info/RECORD
